./.gitignore
./LICENSE
./PKG-INFO
./README.md
./claw.py
./pyproject.toml
claw_cli-1.0.0.dist-info/METADATA
claw_cli-1.0.0.dist-info/WHEEL
claw_cli-1.0.0.dist-info/entry_points.txt
claw_cli-1.0.0.dist-info/licenses/LICENSE
claw_cli-1.0.0.dist-info/RECORD
