Metadata-Version: 2.4
Name: claw-cli
Version: 1.0.0
Summary: CLaude AnyWhere - Remote control for Claude Code from your phone
Project-URL: Homepage, https://github.com/raullenchai/claw
Project-URL: Repository, https://github.com/raullenchai/claw
Project-URL: Issues, https://github.com/raullenchai/claw/issues
Author: raullenchai
License-Expression: MIT
License-File: LICENSE
Keywords: claude,cli,remote,terminal,tmux
Classifier: Development Status :: 4 - Beta
Classifier: Environment :: Console
Classifier: Intended Audience :: Developers
Classifier: License :: OSI Approved :: MIT License
Classifier: Operating System :: OS Independent
Classifier: Programming Language :: Python :: 3
Classifier: Programming Language :: Python :: 3.8
Classifier: Programming Language :: Python :: 3.9
Classifier: Programming Language :: Python :: 3.10
Classifier: Programming Language :: Python :: 3.11
Classifier: Programming Language :: Python :: 3.12
Classifier: Topic :: Utilities
Requires-Python: >=3.8
